{
  "runId": "run-moasngcn",
  "repoRoot": "D:\\source-codes\\kanbanstr",
  "engine": "plugin",
  "startedAt": "2026-04-23T01:19:31.463Z",
  "lastUpdated": "2026-04-23T04:42:13.138Z",
  "currentPhase": null,
  "phaseStartedAt": {
    "plan": "2026-04-23T01:19:31.463Z",
    "map": "2026-04-23T02:52:12.057Z",
    "break": "2026-04-23T03:52:46.008Z",
    "cover": "2026-04-23T04:06:45.810Z",
    "implement": "2026-04-23T04:19:16.515Z",
    "refactor": "2026-04-23T04:32:40.162Z",
    "finish": "2026-04-23T04:39:24.878Z"
  },
  "phaseStatus": {
    "plan": "completed",
    "map": "completed",
    "break": "completed",
    "cover": "completed",
    "implement": "completed",
    "refactor": "completed",
    "finish": "awaiting-approval"
  },
  "tests": {
    "total": 0,
    "passing": 0,
    "failing": 0,
    "skipped": 0
  },
  "coverage": {
    "baseline": null,
    "current": null
  },
  "seamsFound": 0,
  "dependenciesBroken": 0,
  "artifacts": [
    "D:\\source-codes\\kanbanstr\\plan\\plan.md",
    "D:\\source-codes\\kanbanstr\\plan\\seams-and-dependencies.md",
    "D:\\source-codes\\kanbanstr\\src\\lib\\stores\\buildThread.test.ts",
    "D:\\source-codes\\kanbanstr\\src\\lib\\components\\CardDetails.pinning.test.ts",
    "D:\\source-codes\\kanbanstr\\src\\lib\\stores\\comments.ts",
    "D:\\source-codes\\kanbanstr\\src\\test\\comments.store.test.ts",
    "D:\\source-codes\\kanbanstr\\src\\lib\\components\\CardComments.svelte",
    "D:\\source-codes\\kanbanstr\\src\\lib\\components\\CommentThread.svelte",
    "D:\\source-codes\\kanbanstr\\src\\lib\\components\\CardDetails.svelte",
    "D:\\source-codes\\kanbanstr\\CHANGELOG.md",
    "D:\\source-codes\\kanbanstr\\README.md",
    "D:\\source-codes\\kanbanstr\\plan\\pr-description.md"
  ]
}